{
  "for_date": "2026-06-09",
  "generated_at": "2026-06-08T13:53:53.122918+09:00",
  "candidates": [
    {
      "product": {
        "name": "코지스 전동 충전식 원터치 소금 후추그라인더 1세트 200ml",
        "price": "42,800원",
        "original_price": "",
        "discount_rate": 0,
        "image_url": "https://shopping-phinf.pstatic.net/main_5733255/57332559712.8.jpg",
        "product_url": "https://link.coupang.com/re/PCSNAVERPCSDP?pageKey=8923523045&ctag=8923523045&lptag=I26078683398&itemId=26078683398&vendorItemId=93059656519&spec=10305198",
        "badge": "쿠팡",
        "brand": "",
        "category": "보관/밀폐용기",
        "category_hint": "주방",
        "mall_name": "쿠팡",
        "source": "naver_shopping",
        "scraped_at": "2026-06-08T04:53:18.973603"
      },
      "post_text": "",
      "image_url": "https://shopping-phinf.pstatic.net/main_5733255/57332559712.8.jpg",
      "detail_images": [
        "https://shopping-phinf.pstatic.net/main_5733255/57332559712.8.jpg"
      ],
      "product_code": "",
      "status": "pending"
    },
    {
      "product": {
        "name": "PONTE 독일 다기능 스팀청소기 핸디 고압 화이트 PVC-4809",
        "price": "62,000원",
        "original_price": "",
        "discount_rate": 0,
        "image_url": "https://shopping-phinf.pstatic.net/main_5915999/59159994257.10.jpg",
        "product_url": "https://link.coupang.com/re/PCSNAVERPCSDP?pageKey=9414993291&ctag=9414993291&lptag=I27976259146&itemId=27976259146&vendorItemId=94381995919&spec=10305198",
        "badge": "쿠팡",
        "brand": "폰테",
        "category": "스팀청소기",
        "category_hint": "생활",
        "mall_name": "쿠팡",
        "source": "naver_shopping",
        "scraped_at": "2026-06-08T04:53:29.861408"
      },
      "post_text": "",
      "image_url": "https://shopping-phinf.pstatic.net/main_5915999/59159994257.10.jpg",
      "detail_images": [
        "https://shopping-phinf.pstatic.net/main_5915999/59159994257.10.jpg"
      ],
      "product_code": "",
      "status": "pending"
    }
  ]
}