{
  "for_date": "2026-07-11",
  "generated_at": "2026-07-10T01:48:22.585783+09:00",
  "candidates": [
    {
      "product": {
        "name": "도도풋케어 해머발각질제거기 무선전동 굳은살제거 157g 1개 1개입",
        "price": "17,900원",
        "original_price": "",
        "discount_rate": 0,
        "image_url": "https://shopping-phinf.pstatic.net/main_5889797/58897974967.7.jpg",
        "product_url": "https://link.coupang.com/re/PCSNAVERPCSDP?pageKey=9296360483&ctag=9296360483&lptag=I27536178863&itemId=27536178863&vendorItemId=94500708342&spec=10305199",
        "badge": "쿠팡",
        "brand": "도도풋케어",
        "category": "발각질제거기",
        "category_hint": "건강",
        "mall_name": "쿠팡",
        "source": "naver_shopping",
        "scraped_at": "2026-07-09T16:45:28.010595"
      },
      "post_text": "발이 너무 아파서 잠도 안 오는 날이 있잖아\n그런데 발 각질 제거하려고 수건으로 뻐끔뻐끔 문지르다 보니 더 아파질 때가 많더라\n근데 이 무선 전동 굳은살 제거기 쓸 때마다 발이 뻣뻣하게 않더라고\n리뷰 보니까 산 사람들이 하나같이 왜 이제 샀냐고 하더라\n✔ 발에 각질이 많을 때는 이거로 간단하게 제거하고, 뒤꿈치에는 각질 제거 스톤으로 부드럽게 갈아주면 더 좋더라\n✔ 발에 물기가 있을 때 사용하지 말고, 완전히 마른 후에 사용하면 더 효과적이더라\n\n#건강관리 #발건강 #각질제거 #생활꿀템 #건강생활",
      "image_url": "https://shopping-phinf.pstatic.net/main_5889797/58897974967.7.jpg",
      "detail_images": [
        "https://shopping-phinf.pstatic.net/main_5889797/58897974967.7.jpg"
      ],
      "product_code": "",
      "status": "pending"
    },
    {
      "product": {
        "name": "페이스팩토리 전동 다이아필 각질제거기 화이트 FF-27",
        "price": "43,010원",
        "original_price": "",
        "discount_rate": 0,
        "image_url": "https://shopping-phinf.pstatic.net/main_5027322/50273223171.12.jpg",
        "product_url": "https://link.coupang.com/re/PCSNAVERPCSDP?pageKey=8327675475&ctag=8327675475&lptag=I24041145299&itemId=24041145299&vendorItemId=91061374698&spec=10305197",
        "badge": "쿠팡",
        "brand": "페이스팩토리",
        "category": "발각질제거기",
        "category_hint": "건강",
        "mall_name": "쿠팡",
        "source": "naver_shopping",
        "scraped_at": "2026-07-09T16:45:28.010825"
      },
      "post_text": "피부과 가는 거 부담스러운데 매끈한 피부는 갖고 싶은 사람 모여봐! 🙋‍♀️\n\n환절기만 되면 피부 푸석하고 각질 때문에 화장 뜨는 거 진짜 스트레스더라고. 특히 혼자 살면 피부 관리샵 꾸준히 가기도 쉽지 않고, 집에서 혼자 하려니 귀찮고 번거로운 게 많잖아.\n\n근데 이거 써보고 깜짝 놀랐음. 전동으로 미세하게 돌아가는 헤드가 묵은 각질이랑 노폐물을 자극 없이 싹 제거해주더라. 피부과에서 쓰는 필링이랑 비슷한 원리인데 집에서 편하게 할 수 있게 나왔음. 쓰고 나면 피부 결이 맨들맨들 보들보들해져서 진짜 감탄했어.\n\n써본 사람들이 다들 피부가 환해지고 화장도 잘 먹는다고 하더라. 난 이거 한 번 쓰고 나서 화장품 흡수도 더 잘 되는 느낌 받았음!\n\n✔샤워하고 나서 물기 없는 얼굴에 가볍게 문질러주면 훨씬 효과 좋더라.\n✔일주일에 1~2번만 써도 피부가 확 달라지는 거 느껴질 거야! 🥹\n\n내가 쓴 자취 살림 꿀템들, 프로필 링크에 표로 깔끔하게 다 정리해뒀어! 팔로우하고 꼭 확인해보고 돈 아껴ㅠㅠ\n\n#피부관리 #홈케어 #각질제거 #건강템 #뷰티템",
      "image_url": "https://shopping-phinf.pstatic.net/main_5027322/50273223171.12.jpg",
      "detail_images": [
        "https://shopping-phinf.pstatic.net/main_5027322/50273223171.12.jpg"
      ],
      "product_code": "",
      "status": "pending"
    }
  ]
}