{
  "for_date": "2026-07-21",
  "generated_at": "2026-07-20T01:38:18.752525+09:00",
  "candidates": [
    {
      "product": {
        "name": "마이웰 국산 가정용 혈압계 디지털 자동전자 혈압측정기 MY-1999",
        "price": "54,900원",
        "original_price": "",
        "discount_rate": 0,
        "image_url": "https://shopping-phinf.pstatic.net/main_6077731/60777317333.jpg",
        "product_url": "https://link.coupang.com/re/PCSNAVERPCSDP?pageKey=1289359384&ctag=1289359384&lptag=l235209900831&itemId=39200893051&vendorItemId=90478067034&spec=10305198",
        "badge": "쿠팡",
        "brand": "마이웰",
        "category": "혈압계",
        "category_hint": "건강",
        "mall_name": "쿠팡",
        "source": "naver_shopping",
        "scraped_at": "2026-07-19T16:37:08.885044"
      },
      "post_text": "요즘 건강 체크에 신경 더 많이 쓰게 된 사람 많을 거 같아\n나도 최근에 혈압측정기 샀어\n정말 편리하고 정확하더라",
      "image_url": "https://shopping-phinf.pstatic.net/main_6077731/60777317333.jpg",
      "detail_images": [
        "https://shopping-phinf.pstatic.net/main_6077731/60777317333.jpg"
      ],
      "product_code": "",
      "status": "pending"
    },
    {
      "product": {
        "name": "전동그라인더 2개 MS3361 소금 후추 전용 그라인더 코스트코",
        "price": "35,980원",
        "original_price": "",
        "discount_rate": 0,
        "image_url": "https://shopping-phinf.pstatic.net/main_5979414/59794141083.jpg",
        "product_url": "https://link.coupang.com/re/PCSNAVERPCSDP?pageKey=9507766006&ctag=9507766006&lptag=I28330825814&itemId=28330825814&vendorItemId=95283211257&spec=10305199",
        "badge": "쿠팡",
        "brand": "",
        "category": "보관/밀폐용기",
        "category_hint": "주방",
        "mall_name": "쿠팡",
        "source": "naver_shopping",
        "scraped_at": "2026-07-19T16:37:05.833661"
      },
      "post_text": "요즘 집에서 제일 손 많이 가는 게 이 코스트코\n궁금하면 댓글 봐봐",
      "image_url": "https://shopping-phinf.pstatic.net/main_5979414/59794141083.jpg",
      "detail_images": [
        "https://shopping-phinf.pstatic.net/main_5979414/59794141083.jpg"
      ],
      "product_code": "",
      "status": "pending"
    },
    {
      "product": {
        "name": "씨즌M닷컴 카카오프렌즈 휴대용 UV살균 칫솔케이스 라이언 RYAN 라이언001",
        "price": "27,900원",
        "original_price": "",
        "discount_rate": 0,
        "image_url": "https://shopping-phinf.pstatic.net/main_2386835/23868356238.jpg",
        "product_url": "https://link.coupang.com/re/PCSNAVERPCSDP?pageKey=1501239636&ctag=1501239636&lptag=P1501239636&itemId=2577588578&vendorItemId=70569850445&spec=10305199",
        "badge": "쿠팡",
        "brand": "",
        "category": "구강청정기",
        "category_hint": "생활",
        "mall_name": "쿠팡",
        "source": "naver_shopping",
        "scraped_at": "2026-07-19T16:37:07.466953"
      },
      "post_text": "칫솔 관리가 귀찮을 때 이거 쓰면 간편하더라\n사진에 나와있는 제품은 라이언 케이스야\n이거 쓰고 칫솔 관리가 확 쉬워졌음",
      "image_url": "https://shopping-phinf.pstatic.net/main_2386835/23868356238.jpg",
      "detail_images": [
        "https://shopping-phinf.pstatic.net/main_2386835/23868356238.jpg"
      ],
      "product_code": "",
      "status": "pending"
    },
    {
      "product": {
        "name": "제노벤 스팀청소기 고압 살균 올인원 가정용 차량용 화이트 CNT-QX-SXYT",
        "price": "144,900원",
        "original_price": "",
        "discount_rate": 0,
        "image_url": "https://shopping-phinf.pstatic.net/main_5634717/56347172178.3.jpg",
        "product_url": "https://link.coupang.com/re/PCSNAVERPCSDP?pageKey=8867649453&ctag=8867649453&lptag=I25865217656&itemId=25865217656&vendorItemId=93203771805&spec=10305198",
        "badge": "쿠팡",
        "brand": "",
        "category": "스팀청소기",
        "category_hint": "생활",
        "mall_name": "쿠팡",
        "source": "naver_shopping",
        "scraped_at": "2026-07-19T16:37:08.081991"
      },
      "post_text": "청소하기가 너무 귀찮을 때 이런 게 있었으면 좋겠다 싶었어\n사진 보니까 이거 쓰면 청소하기가 쉬울 것 같고\n화이트색상이 되게 깨끗해 보여서 좋더라",
      "image_url": "https://shopping-phinf.pstatic.net/main_5634717/56347172178.3.jpg",
      "detail_images": [
        "https://shopping-phinf.pstatic.net/main_5634717/56347172178.3.jpg"
      ],
      "product_code": "",
      "status": "pending"
    }
  ]
}